flow_control/__init__.py
flow_control/controller.py
flow_control/test.py
flow_control-2.0.0.dist-info/METADATA
flow_control-2.0.0.dist-info/WHEEL
flow_control-2.0.0.dist-info/top_level.txt
flow_control-2.0.0.dist-info/RECORD
