Metadata-Version: 2.1
Name: flow-control
Version: 2.0.0
Summary: A flow control packages,control QPS
Home-page: https://github.com/mt6979/flow_control
Author: liuyancong
Author-email: 1437255447@qq.com
License: UNKNOWN
Platform: UNKNOWN
Classifier: Programming Language :: Python :: 3
Classifier: License :: OSI Approved :: MIT License
Classifier: Operating System :: OS Independent
Requires-Python: >=2.7
